mediainfo/__init__.py
mediainfo/video.py
mediainfo_py-0.1.3.dist-info/licenses/LICENSE
mediainfo_py-0.1.3.dist-info/METADATA
mediainfo_py-0.1.3.dist-info/WHEEL
mediainfo_py-0.1.3.dist-info/top_level.txt
mediainfo_py-0.1.3.dist-info/RECORD
