Metadata-Version: 2.4
Name: mediainfo-py
Version: 0.1.3
Summary: Lightweight FFmpeg-based video metadata extractor
Author: Aditya Katyal
License: MIT License
Requires-Python: >=3.8
License-File: LICENSE
Requires-Dist: ffmpeg-python
Dynamic: license-file
